pyaitools/__init__.py
pyaitools/detect.py
pyaitools/feedback.py
pyaitools/guard.py
pyaitools/line_detect.py
pyaitools/loss.py
pyaitools/mail.py
pyaitools/plot.py
pyaitools/pprofile.py
pyaitools/similar.py
pyaitools/stress.py
pyaitools/theT.py
pyaitools/utils.py
pyaitools/weight_pooled_output.py
pyaitools-1.4.27.dist-info/LICENSE
pyaitools-1.4.27.dist-info/METADATA
pyaitools-1.4.27.dist-info/WHEEL
pyaitools-1.4.27.dist-info/entry_points.txt
pyaitools-1.4.27.dist-info/top_level.txt
pyaitools-1.4.27.dist-info/RECORD
